jsonql/__init__.py
jsonql/browser.py
jsonql/core.py
jsonql/query.py
jsonql_db-0.1.5.dist-info/licenses/LICENSE
jsonql_db-0.1.5.dist-info/METADATA
jsonql_db-0.1.5.dist-info/WHEEL
jsonql_db-0.1.5.dist-info/top_level.txt
jsonql_db-0.1.5.dist-info/RECORD
