Metadata-Version: 2.4
Name: jsonql-db
Version: 0.1.5
Summary: A lightweight, file-based JSON database with SQL-like interface
Home-page: https://github.com/takouzlo/jsonql-db
Author: FBF
Author-email: f.bfalik@gmail.com
License: MIT
Keywords: json database sqlite alternative lightweight file-based
Classifier: Development Status :: 4 - Beta
Classifier: Intended Audience :: Developers
Classifier: Operating System :: OS Independent
Classifier: Programming Language :: Python :: 3
Classifier: Programming Language :: Python :: 3.7
Classifier: Programming Language :: Python :: 3.8
Classifier: Programming Language :: Python :: 3.9
Classifier: Programming Language :: Python :: 3.10
Classifier: Programming Language :: Python :: 3.11
Classifier: Topic :: Database
Classifier: Topic :: Software Development :: Libraries :: Python Modules
Requires-Python: >=3.7
License-File: LICENSE
Provides-Extra: browser
Requires-Dist: flet>=0.25.0; extra == "browser"
Dynamic: author
Dynamic: author-email
Dynamic: classifier
Dynamic: description
Dynamic: description-content-type
Dynamic: home-page
Dynamic: keywords
Dynamic: license
Dynamic: license-file
Dynamic: provides-extra
Dynamic: requires-python
Dynamic: summary
